[{"WORKSITE_STATE":"CA","EMPLOYER_NAME":"APPLE INC.","JOB_TITLE":"VICE PRESIDENT","AVERAGE_WAGE_RATE_OF_PAY":600000},{"WORKSITE_STATE":"CA","EMPLOYER_NAME":"APPLE INC.","JOB_TITLE":"SPECIAL CREATIVE","AVERAGE_WAGE_RATE_OF_PAY":500000},{"WORKSITE_STATE":"CA","EMPLOYER_NAME":"WESTFIELD LLC","JOB_TITLE":"GLOBAL HEAD OF FINANCE AND INFORMATION TECHNOLOGY","AVERAGE_WAGE_RATE_OF_PAY":490000},{"WORKSITE_STATE":"CA","EMPLOYER_NAME":"WESTFIELD LLC","JOB_TITLE":"EXECUTIVE VICE PRESIDENT, LEASING","AVERAGE_WAGE_RATE_OF_PAY":425000},{"WORKSITE_STATE":"CA","EMPLOYER_NAME":"MAINFREIGHT INC.","JOB_TITLE":"CHIEF EXECUTIVE OFFICER","AVERAGE_WAGE_RATE_OF_PAY":410000},{"WORKSITE_STATE":"CA","EMPLOYER_NAME":"THE WEISSCOMM GROUP LTD","JOB_TITLE":"CHIEF FINANCIAL OFFICER","AVERAGE_WAGE_RATE_OF_PAY":400000},{"WORKSITE_STATE":"CA","EMPLOYER_NAME":"TECHNICOLOR, INC.","JOB_TITLE":"CHIEF OPERATING OFFICER","AVERAGE_WAGE_RATE_OF_PAY":389836},{"WORKSITE_STATE":"CA","EMPLOYER_NAME":"APPLE INC.","JOB_TITLE":"MARCOM SR. DIRECTOR","AVERAGE_WAGE_RATE_OF_PAY":375000},{"WORKSITE_STATE":"CA","EMPLOYER_NAME":"TECHNOSOFT CORPORATION","JOB_TITLE":"PROGRAMMER ANALYST","AVERAGE_WAGE_RATE_OF_PAY":370000},{"WORKSITE_STATE":"CA","EMPLOYER_NAME":"LIGHTSPEED MANAGEMENT COMPANY LLC","JOB_TITLE":"PARTNER","AVERAGE_WAGE_RATE_OF_PAY":364608}]
